fourier_gls/__init__.py
fourier_gls/critical_values.py
fourier_gls/fourier_gls.py
fourier_gls/py.typed
fourier_gls/utils.py
fourier_gls/version.py
fourier_gls-1.0.0.dist-info/licenses/LICENSE
fourier_gls-1.0.0.dist-info/METADATA
fourier_gls-1.0.0.dist-info/WHEEL
fourier_gls-1.0.0.dist-info/top_level.txt
fourier_gls-1.0.0.dist-info/RECORD
