Metadata-Version: 2.4
Name: fourier_gls
Version: 1.0.0
Summary: Flexible Fourier Form and Local GLS De-trended Unit Root Tests
Author-email: "Dr. Merwan Roudane" <merwanroudane920@gmail.com>
Maintainer-email: "Dr. Merwan Roudane" <merwanroudane920@gmail.com>
License: MIT
Project-URL: Homepage, https://github.com/merwanroudane/fouriergls
Project-URL: Documentation, https://github.com/merwanroudane/fouriergls#readme
Project-URL: Repository, https://github.com/merwanroudane/fouriergls.git
Project-URL: Issues, https://github.com/merwanroudane/fouriergls/issues
Keywords: econometrics,unit root,time series,fourier,GLS,structural breaks,hypothesis testing,stationarity
Classifier: Development Status :: 5 - Production/Stable
Classifier: Intended Audience :: Science/Research
Classifier: Intended Audience :: Education
Classifier: License :: OSI Approved :: MIT License
Classifier: Operating System :: OS Independent
Classifier: Programming Language :: Python :: 3
Classifier: Programming Language :: Python :: 3.8
Classifier: Programming Language :: Python :: 3.9
Classifier: Programming Language :: Python :: 3.10
Classifier: Programming Language :: Python :: 3.11
Classifier: Programming Language :: Python :: 3.12
Classifier: Topic :: Scientific/Engineering :: Mathematics
Classifier: Topic :: Scientific/Engineering :: Information Analysis
Requires-Python: >=3.8
License-File: LICENSE
Requires-Dist: numpy>=1.20.0
Requires-Dist: scipy>=1.7.0
Provides-Extra: dev
Requires-Dist: pytest>=7.0.0; extra == "dev"
Requires-Dist: pytest-cov>=4.0.0; extra == "dev"
Requires-Dist: black>=22.0.0; extra == "dev"
Requires-Dist: flake8>=5.0.0; extra == "dev"
Requires-Dist: mypy>=1.0.0; extra == "dev"
Provides-Extra: docs
Requires-Dist: sphinx>=5.0.0; extra == "docs"
Requires-Dist: sphinx-rtd-theme>=1.0.0; extra == "docs"
Requires-Dist: numpydoc>=1.5.0; extra == "docs"
Provides-Extra: examples
Requires-Dist: pandas>=1.4.0; extra == "examples"
Requires-Dist: matplotlib>=3.5.0; extra == "examples"
Requires-Dist: statsmodels>=0.13.0; extra == "examples"
Provides-Extra: all
Requires-Dist: fourier_gls[dev,docs,examples]; extra == "all"
Dynamic: license-file
